chakra_mcp/__init__.py
chakra_mcp/__main__.py
chakra_mcp/consts.py
chakra_mcp/server.py
chakra_mcp-0.2.1.dist-info/METADATA
chakra_mcp-0.2.1.dist-info/WHEEL
chakra_mcp-0.2.1.dist-info/entry_points.txt
chakra_mcp-0.2.1.dist-info/top_level.txt
chakra_mcp-0.2.1.dist-info/RECORD
