Metadata-Version: 2.2
Name: chakra-mcp
Version: 0.2.1
Summary: A native MCP server integration for Chakra databases
Author-email: Chakra Labs Team <hi@chakra-labs.com>
License: MIT
Project-URL: Homepage, https://chakra.dev/
Project-URL: Repository, https://github.com/Chakra-Network/mcp-server
Project-URL: Documentation, https://github.com/Chakra-Network/mcp-server#readme
Project-URL: Bug Tracker, https://github.com/Chakra-Network/mcp-server/issues
Keywords: chakra,mcp,database
Classifier: Development Status :: 4 - Beta
Classifier: Intended Audience :: Developers
Classifier: License :: OSI Approved :: MIT License
Classifier: Programming Language :: Python :: 3
Classifier: Programming Language :: Python :: 3.11
Classifier: Topic :: Database
Requires-Python: >=3.11
Requires-Dist: chakra-py>=1.0.17
Requires-Dist: mcp[cli]>=1.2.1
